DutchDraw/DutchDraw.py
DutchDraw/__init__.py
DutchDraw-0.0.2.dist-info/LICENSE
DutchDraw-0.0.2.dist-info/METADATA
DutchDraw-0.0.2.dist-info/WHEEL
DutchDraw-0.0.2.dist-info/top_level.txt
DutchDraw-0.0.2.dist-info/RECORD
