Metadata-Version: 2.1
Name: DutchDraw
Version: 0.0.2
Summary: Determine (optimal) baselines for binary classification
Home-page: https://github.com/joris-pries/DutchDraw
Author: Etienne van de Bijl, Jan Klein, Joris Pries
Author-email: joris.pries@cwi.nl
License: UNKNOWN
Platform: UNKNOWN
Classifier: Programming Language :: Python :: 3
Classifier: License :: OSI Approved :: MIT License
Classifier: Operating System :: OS Independent
Requires-Python: >=3.6
